duck_jenkins/__init__.py
duck_jenkins/_app.py
duck_jenkins/_model.py
duck_jenkins/_utils.py
duck_jenkins-0.0.25.dist-info/LICENSE
duck_jenkins-0.0.25.dist-info/METADATA
duck_jenkins-0.0.25.dist-info/WHEEL
duck_jenkins-0.0.25.dist-info/top_level.txt
duck_jenkins-0.0.25.dist-info/RECORD
