Metadata-Version: 2.1
Name: duck-jenkins
Version: 0.0.25
Summary: Jenkins build data ETL with DuckDB
Home-page: https://github.com/maxleow/duck-jenkins
Author: Max Leow
Author-email: maxengiu@outlook.com
Project-URL: Bug Tracker, https://github.com/maxleow/duck-jenkins/issues
Classifier: Programming Language :: Python :: 3.7
Classifier: Programming Language :: Python :: 3.8
Classifier: Programming Language :: Python :: 3.9
Classifier: Programming Language :: Python :: 3.10
Classifier: License :: OSI Approved :: MIT License
Classifier: Operating System :: OS Independent
Requires-Python: >=3.7
License-File: LICENSE
Requires-Dist: duckdb
Requires-Dist: pandas
Requires-Dist: requests
Requires-Dist: jsonpath-ng
Requires-Dist: pydantic
Requires-Dist: aiohttp
